cmslib.py
helloworld.py
cmslib-0.0.1.dist-info/METADATA
cmslib-0.0.1.dist-info/WHEEL
cmslib-0.0.1.dist-info/top_level.txt
cmslib-0.0.1.dist-info/RECORD
