Metadata-Version: 2.1
Name: cmslib
Version: 0.0.1
Summary: A standard Python library for CMS distribution
Home-page: UNKNOWN
License: UNKNOWN
Platform: UNKNOWN
Requires-Dist: PyYAML
